LICENSE
README.md
setup.py
dsmlibrary_viz/__init__.py
dsmlibrary_viz/base.py
dsmlibrary_viz/data_viz.py
dsmlibrary_viz/utils.py
dsmlibrary_viz.egg-info/PKG-INFO
dsmlibrary_viz.egg-info/SOURCES.txt
dsmlibrary_viz.egg-info/dependency_links.txt
dsmlibrary_viz.egg-info/requires.txt
dsmlibrary_viz.egg-info/top_level.txt
dsmlibrary_viz/scripts/__init__.py
dsmlibrary_viz/scripts/install_ext.py